{"lon1":{"exact":[["LON1",0,"YBL022C","chrII",177876,181278]],"prefix":[]},"ybr18":{"exact":[],"prefix":["YBR180W","YBR181C","YBR182C","YBR182C-A","YBR183W","YBR184W","YBR185C","YBR186W","YBR187W","YBR188C","YBR189W"]},"agp":{"prefix":["AGP2"],"exact":[]},"fun9":{"exact":[["FUN9",0,"YAL042W","chrI",61316,62564]],"prefix":[]},"mrpl36":{"prefix":[],"exact":[["MRPL36",0,"YBR122C","chrII",483963,484497]]},"ef-1 alp":{"prefix":["EF-1 alpha"],"exact":[]},"ybr001":{"exact":[],"prefix":["YBR001C"]},"ybl04":{"prefix":["YBL049W","YBL048W","YBL047C","YBL046W","YBL045C","YBL044W","YBL043W","YBL042C","YBL041W","YBL040C"],"exact":[]},"ybl090w":{"exact":[["YBL090W",0,"YBL090W","chrII",48821,49355]],"prefix":[]},"cc":{"exact":[],"prefix":["CCR4","CCZ1"]},"ybr001c":{"exact":[["YBR001C",0,"YBR001C","chrII",238942,241285]],"prefix":[]},"flr1":{"exact":[["FLR1",0,"YBR008C","chrII",252563,254210]],"prefix":[]},"gs":{"exact":[],"prefix":["GSE1"]},"tb":{"prefix":["TBS1"],"exact":[]},"yal022c":{"prefix":[],"exact":[["YAL022C",0,"YAL022C","chrI",108877,110431]]},"yal038w":{"prefix":[],"exact":[["YAL038W",0,"YAL038W","chrI",71786,73289]]},"ybl043w":{"exact":[["YBL043W",0,"YBL043W","chrII",136690,137464]],"prefix":[]},"str":{"exact":[],"prefix":["STR1"]},"ybl054w":{"exact":[["YBL054W",0,"YBL054W","chrII",117591,119169]],"prefix":[]},"bu":{"exact":[],"prefix":["BUF2","BUD14","BUD15","BUR5"]},"sup1":{"exact":[["SUP1",0,"YBR143C","chrII",530862,532176]],"prefix":[]},"aar2":{"exact":[["AAR2",0,"YBL074C","chrII",86719,87787]],"prefix":[]},"ats1":{"exact":[["ATS1",0,"YAL020C","chrI",113614,114616]],"prefix":[]},"hdr":{"exact":[],"prefix":["HDR1"]},"ybr127":{"exact":[],"prefix":["YBR127C"]},"ybr029":{"prefix":["YBR029C"],"exact":[]},"ybl112":{"prefix":["YBL112C"],"exact":[]},"yal059c-":{"prefix":["YAL059C-A"],"exact":[]},"aor1":{"exact":[["AOR1",0,"YBR231C","chrII",682173,683085]],"prefix":[]},"taf9":{"prefix":["TAF90"],"exact":[]},"ybr159":{"prefix":["YBR159W"],"exact":[]},"ybr230w-":{"exact":[],"prefix":["YBR230W-A"]},"agp2":{"prefix":[],"exact":[["AGP2",0,"YBR132C","chrII",499645,501436]]},"ybr036":{"exact":[],"prefix":["YBR036C"]},"ybr275":{"exact":[],"prefix":["YBR275C"]},"ybr146":{"exact":[],"prefix":["YBR146W"]},"sl":{"prefix":["SLT2","SLA1","SLT11","SLM4","SLX2","SLI15","SLX1","SLM6"],"exact":[]},"fe":{"exact":[],"prefix":["FES1"]},"pol":{"prefix":["POL12","POL30"],"exact":[]},"swc3":{"prefix":[],"exact":[["SWC3",0,"YAL011W","chrI",132201,134079]]},"gcv3":{"exact":[["GCV3",0,"YAL044C","chrI",57950,58463]],"prefix":[]},"yal016w":{"prefix":[],"exact":[["YAL016W",0,"YAL016W","chrI",124879,126787]]},"aim3":{"prefix":[],"exact":[["AIM3",0,"YBR108W","chrII",454815,457659]]},"saf49":{"exact":[["SAF49",0,"YAR003W","chrI",155006,156287]],"prefix":[]},"yal035c":{"prefix":["YAL035C-A"],"exact":[]},"fur4":{"prefix":[],"exact":[["FUR4",0,"YBR021W","chrII",281442,283344]]},"ybl034":{"prefix":["YBL034C"],"exact":[]},"ybl088":{"prefix":["YBL088C"],"exact":[]},"yar060":{"exact":[],"prefix":["YAR060C"]},"ppd1":{"prefix":[],"exact":[["PPD1",0,"YBR140C","chrII",517343,526622]]},"yar015w":{"prefix":[],"exact":[["YAR015W",0,"YAR015W","chrI",169369,170290]]},"fmp23":{"exact":[["FMP23",0,"YBR047W","chrII",331830,332358]],"prefix":[]},"vps10":{"exact":[["VPS10",0,"YBL017C","chrII",186846,191586]],"prefix":[]},"yal003":{"exact":[],"prefix":["YAL003W"]},"orc":{"prefix":["ORC2"],"exact":[]},"arp10":{"prefix":["ARP100"],"exact":[]},"dt":{"exact":[],"prefix":["DTR1"]},"pim":{"prefix":["PIM1"],"exact":[]},"qd":{"prefix":["QDR3"],"exact":[]},"ypc":{"exact":[],"prefix":["YPC1"]},"dur8":{"prefix":["DUR80"],"exact":[]},"rps9b":{"exact":[["RPS9B",0,"YBR189W","chrII",604502,605503]],"prefix":[]},"ybl055":{"exact":[],"prefix":["YBL055C"]},"ybr152w":{"exact":[["YBR152W",0,"YBR152W","chrII",546369,547245]],"prefix":[]},"ybr057":{"exact":[],"prefix":["YBR057C"]},"ybr145w":{"prefix":[],"exact":[["YBR145W",0,"YBR145W","chrII",533755,534811]]},"um":{"exact":[],"prefix":["UMP1"]},"shmt":{"prefix":["SHMT1"],"exact":[]},"spo7":{"prefix":[],"exact":[["SPO7",0,"YAL009W","chrI",135855,136635]]},"yal062":{"prefix":["YAL062W"],"exact":[]},"vma2":{"prefix":[],"exact":[["VMA2",0,"YBR127C","chrII",491262,492816]]},"vat2":{"exact":[["VAT2",0,"YBR127C","chrII",491262,492816]],"prefix":[]},"mrp":{"exact":[],"prefix":["MRP21","MRP50","MRPL16","MRPL36","MRPS9","MRPS5","MRPL37","MRPL27"]},"ar":{"prefix":["ARA1","ARL1","ARP100","ARC40","ARO4"],"exact":[]},"rpl":{"prefix":["RPL32","RPL23A","RPL19B","RPL4A","RPL19A","RPL21A"],"exact":[]},"ybr138":{"prefix":["YBR138C"],"exact":[]},"yal058c-a":{"prefix":[],"exact":[["YAL058C-A",0,"YAL056C-A","chrI",38696,39047]]},"oa":{"prefix":["OAF1"],"exact":[]},"bit2":{"exact":[["BIT2",0,"YBR270C","chrII",742755,744393]],"prefix":[]},"mrpl":{"exact":[],"prefix":["MRPL16","MRPL36","MRPL37","MRPL27"]},"tif32":{"exact":[["TIF32",0,"YBR079C","chrII",395376,398271]],"prefix":[]},"flc":{"exact":[],"prefix":["FLC2"]},"htb2":{"exact":[["HTB2",0,"YBL002W","chrII",236494,236890]],"prefix":[]},"ybr207w":{"exact":[["YBR207W",0,"YBR207W","chrII",635140,636538]],"prefix":[]},"aro4":{"exact":[["ARO4",0,"YBR249C","chrII",716876,717989]],"prefix":[]},"ybr110":{"prefix":["YBR110W"],"exact":[]},"ybr109w":{"prefix":["YBR109W-A"],"exact":[]},"erv1":{"prefix":["ERV15"],"exact":[]},"grx7":{"prefix":[],"exact":[["GRX7",0,"YBR014C","chrII",266724,267336]]},"rps10":{"exact":[],"prefix":["RPS102","RPS101"]},"avt5":{"exact":[["AVT5",0,"YBL089W","chrII",49570,50950]],"prefix":[]},"su":{"exact":[],"prefix":["SUS1","SUP45","SUP47","SUP1","SUP46","SUL1"]},"dad":{"exact":[],"prefix":["DAD3"]},"ybr30":{"exact":[],"prefix":["YBR300C","YBR301W","YBR302C"]},"ybl107w-":{"exact":[],"prefix":["YBL107W-A"]},"ybl039w-b":{"exact":[["YBL039W-B",0,"YBL039W-B","chrII",143395,143575]],"prefix":[]},"ybr058c-a":{"prefix":[],"exact":[["YBR058C-A",0,"YBR058C-A","chrII",356321,356564]]},"alg14":{"exact":[["ALG14",0,"YBR070C","chrII",379217,379931]],"prefix":[]},"cps30":{"prefix":[],"exact":[["CPS30",0,"YBR175W","chrII",582402,583350]]},"yal055":{"exact":[],"prefix":["YAL055W"]},"cdc24":{"prefix":[],"exact":[["CDC24",0,"YAL041W","chrI",62840,65405]]},"pr":{"prefix":["PRP45","PRM9","PRS4","PRX1","PRE7","PRS3","PRP6","PRP5"],"exact":[]},"pho6":{"prefix":[],"exact":[["PHO6",0,"YBR240C","chrII",700484,701837]]},"ybr022w":{"prefix":[],"exact":[["YBR022W",0,"YBR022W","chrII",283737,284271]]},"b":{"exact":[],"prefix":["BDH2","BDH1","BUF2","BUD14","BNA4","BRN1","BOI1","BOB1","BUD15","BUR5","BAP2","BYP1","BEM1","BIT2","BSD2"]},"atg14":{"prefix":[],"exact":[["ATG14",0,"YBR128C","chrII",493074,494109]]},"ybr063c":{"prefix":[],"exact":[["YBR063C",0,"YBR063C","chrII",366967,368182]]},"ybr280":{"prefix":["YBR280C"],"exact":[]},"scs":{"exact":[],"prefix":["SCS22"]},"odp1":{"exact":[["ODP1",0,"YBR034C","chrII",304929,305976]],"prefix":[]},"ybr040w":{"prefix":[],"exact":[["YBR040W",0,"YBR040W","chrII",316967,317864]]},"hss":{"exact":[],"prefix":["HSS1"]},"ybr089c":{"prefix":["YBR089C-A"],"exact":[]},"rbp1":{"exact":[["RBP1",0,"YBR212W","chrII",647880,649899]],"prefix":[]},"ybr076c-":{"exact":[],"prefix":["YBR076C-A"]},"yar018c":{"prefix":[],"exact":[["YAR018C",0,"YAR018C","chrI",170390,171698]]},"dem":{"exact":[],"prefix":["DEM1"]},"ybr210w":{"exact":[["YBR210W",0,"YBR210W","chrII",645544,645973]],"prefix":[]},"brn1":{"exact":[["BRN1",0,"YBL097W","chrII",40827,43092]],"prefix":[]},"ybr171":{"prefix":["YBR171W"],"exact":[]},"tpd":{"exact":[],"prefix":["TPD3"]},"mrp5":{"prefix":["MRP50"],"exact":[]},"mi":{"exact":[],"prefix":["MIS1"]},"ut":{"prefix":["UTP20"],"exact":[]},"sse":{"prefix":["SSE2"],"exact":[]},"pyk1":{"prefix":[],"exact":[["PYK1",0,"YAL038W","chrI",71786,73289]]},"aac2":{"exact":[["AAC2",0,"YBL030C","chrII",163043,164000]],"prefix":[]},"grf2":{"exact":[["GRF2",0,"YBR049C","chrII",334383,336816]],"prefix":[]},"cos2":{"exact":[["COS2",0,"YBR302C","chrII",810333,811473]],"prefix":[]},"cdc2":{"prefix":["CDC24","CDC27","CDC28"],"exact":[]},"ybr126w-b":{"exact":[["YBR126W-B",0,"YBR126W-B","chrII",490920,491064]],"prefix":[]},"ybr07":{"prefix":["YBR070C","YBR071W","YBR072W","YBR072C-A","YBR073W","YBR074W","YBR075W","YBR076W","YBR076C-A","YBR077C","YBR078W","YBR079C"],"exact":[]},"chs4":{"exact":[["CHS4",0,"YBL061C","chrII",105317,107408]],"prefix":[]},"ybl059c":{"prefix":["YBL059C-A"],"exact":[]},"ybr095":{"exact":[],"prefix":["YBR095C"]},"fun20":{"prefix":[],"exact":[["FUN20",0,"YAL032C","chrI",83335,84475]]},"srm5":{"exact":[["SRM5",0,"YBR160W","chrII",560071,560968]],"prefix":[]},"ybl107c":{"exact":[["YBL107C",0,"YBL107C","chrII",9960,10551]],"prefix":[]},"kap10":{"exact":[],"prefix":["KAP104"]},"rc":{"prefix":["RCR1"],"exact":[]},"ybr166c":{"exact":[["YBR166C",0,"YBR166C","chrII",569836,571195]],"prefix":[]},"ybr084w":{"exact":[["YBR084W",0,"YBR084W","chrII",411047,413975]],"prefix":[]},"tcm62":{"prefix":[],"exact":[["TCM62",0,"YBR044C","chrII",324336,326058]]},"mst2":{"prefix":["MST28"],"exact":[]},"ybr265w":{"exact":[["YBR265W",0,"YBR265W","chrII",738576,739539]],"prefix":[]},"slm6":{"exact":[["SLM6",0,"YBR266C","chrII",739930,740383]],"prefix":[]},"tsc":{"exact":[],"prefix":["TSC3","TSC10"]},"dlp":{"prefix":["DLP2"],"exact":[]},"yal034":{"prefix":["YAL034C-B","YAL034W-A","YAL034C"],"exact":[]},"aqr2":{"exact":[["AQR2",0,"YBR043C","chrII",321875,323945]],"prefix":[]},"ybl062":{"prefix":["YBL062W"],"exact":[]},"ccr4":{"exact":[["CCR4",0,"YAL021C","chrI",110846,113360]],"prefix":[]},"ybr242":{"exact":[],"prefix":["YBR242W"]},"kh":{"prefix":["KHD1"],"exact":[]},"ak":{"prefix":["AKL1"],"exact":[]},"mis":{"exact":[],"prefix":["MIS1"]},"pk":{"exact":[],"prefix":["PKC1"]},"ybr214":{"exact":[],"prefix":["YBR214W"]},"ede1":{"prefix":[],"exact":[["EDE1",0,"YBL047C","chrII",127897,132043]]},"kap":{"exact":[],"prefix":["KAP104"]},"ybr223":{"prefix":["YBR223C","YBR223W-A"],"exact":[]},"ybr060":{"exact":[],"prefix":["YBR060C"]},"ybr184":{"prefix":["YBR184W"],"exact":[]},"ybl003":{"prefix":["YBL003C"],"exact":[]},"ipp1":{"exact":[["IPP1",0,"YBR011C","chrII",257109,257973]],"prefix":[]},"yar002w":{"prefix":[],"exact":[["YAR002W",0,"YAR002W","chrI",152258,153878]]},"coq":{"prefix":["COQ1"],"exact":[]},"smy":{"exact":[],"prefix":["SMY2"]},"ics2":{"prefix":[],"exact":[["ICS2",0,"YBR157C","chrII",553536,554304]]},"ybr048":{"prefix":["YBR048W"],"exact":[]},"ybl097":{"prefix":["YBL097W"],"exact":[]},"mal31":{"exact":[["MAL31",0,"YBR298C","chrII",802624,804469]],"prefix":[]},"paf":{"prefix":["PAF1"],"exact":[]},"yar029":{"prefix":["YAR029W"],"exact":[]},"ybr182c-a":{"prefix":[],"exact":[["YBR182C-A",0,"YBR182C-A","chrII",595355,595550]]},"scr1":{"prefix":[],"exact":[["SCR1",0,"YAL015C","chrI",126903,128103]]},"yal040c":{"prefix":[],"exact":[["YAL040C",0,"YAL040C","chrI",65778,67521]]}}